trustwise/__init__.py
trustwise/callback.py
trustwise/config.py
trustwise/models.py
trustwise/request.py
trustwise-3.1.4.dist-info/LICENSE
trustwise-3.1.4.dist-info/METADATA
trustwise-3.1.4.dist-info/WHEEL
trustwise-3.1.4.dist-info/top_level.txt
trustwise-3.1.4.dist-info/RECORD
