Metadata-Version: 2.1
Name: trustwise
Version: 3.1.4
Summary: Trustwise PyPi Package
Home-page: https://github.com/trustwiseai/trustwise
Author: Trustwise
Author-email: nihal@trustwise.ai
Classifier: License :: OSI Approved :: MIT License
Classifier: Programming Language :: Python :: 3
Classifier: Programming Language :: Python :: 3.7
Classifier: Programming Language :: Python :: 3.8
Classifier: Programming Language :: Python :: 3.9
License-File: LICENSE
Requires-Dist: llama-index ~=0.9.36
Requires-Dist: pydantic ~=2.5.3
Requires-Dist: requests ~=2.31.0
